terevintosoftware/__init__.py
terevintosoftware/pkce_client/__init__.py
terevintosoftware/pkce_client/login_client.py
terevintosoftware/pkce_client/login_config.py
terevintosoftware/pkce_client/pkce_token.py
terevintosoftware/pkce_client/token_config_map.py
terevintosoftware/pkce_client/internal/__init__.py
terevintosoftware/pkce_client/internal/helpers.py
terevintosoftware/pkce_client/internal/oauth_http_handler.py
terevintosoftware/pkce_client/internal/oauth_http_server.py
TerevintoSoftware.PkceClient-0.1.0.dist-info/LICENSE
TerevintoSoftware.PkceClient-0.1.0.dist-info/METADATA
TerevintoSoftware.PkceClient-0.1.0.dist-info/WHEEL
TerevintoSoftware.PkceClient-0.1.0.dist-info/top_level.txt
TerevintoSoftware.PkceClient-0.1.0.dist-info/RECORD
