Metadata-Version: 2.1
Name: TerevintoSoftware.PkceClient
Version: 0.1.0
Summary: A Python package to deal with OAuth PKCE authentication flow to generate JWT tokens from desktop apps.
Author-email: Camilo Terevinto <software@camiloterevinto.com>
License: MIT License
Project-URL: Homepage, https://github.com/CamiloTerevinto/TerevintoSoftware.PythonPkceClient
Project-URL: Bug Tracker, https://github.com/CamiloTerevinto/TerevintoSoftware.PythonPkceClient/issues
Keywords: oauth,oidc,pkce
Classifier: Programming Language :: Python :: 3
Classifier: License :: OSI Approved :: MIT License
Classifier: Operating System :: OS Independent
Requires-Python: >=3.8
License-File: LICENSE
Requires-Dist: requests
